{"_path":"/en/grid","_dir":"en","_draft":false,"_partial":false,"_locale":"","title":"Grid Gongge","description":"","body":{"type":"root","children":[{"type":"element","tag":"h1","props":{"id":"grid-gongge"},"children":[{"type":"text","value":"Grid Gongge"}]},{"type":"element","tag":"h3","props":{"id":"introduce"},"children":[{"type":"text","value":"introduce"}]},{"type":"element","tag":"p","props":{},"children":[{"type":"text","value":"The grid can divide the page into equal-width blocks in the horizontal direction for displaying content or page navigation."}]},{"type":"element","tag":"h2","props":{"id":"code-demo"},"children":[{"type":"text","value":"Code Demo"}]},{"type":"element","tag":"h3","props":{"id":"basic-usage"},"children":[{"type":"text","value":"Basic usage"}]},{"type":"element","tag":"p","props":{},"children":[{"type":"text","value":"Use the "},{"type":"element","tag":"code","props":{"className":[]},"children":[{"type":"text","value":"icon"}]},{"type":"text","value":" attribute to set the icon in the grid, and the "},{"type":"element","tag":"code","props":{"className":[]},"children":[{"type":"text","value":"text"}]},{"type":"text","value":" attribute to set the text content."}]},{"type":"element","tag":"pre","props":{"className":"language-html shiki shiki-themes min-light min-dark","code":"<z-grid>\n   <z-grid-item v-for=\"i in 4\" :key=\"i\" icon=\"image\" text=\"text\" />\n</z-grid>\n","language":"html","meta":"","style":""},"children":[{"type":"element","tag":"code","props":{"__ignoreMap":""},"children":[{"type":"element","tag":"span","props":{"class":"line","line":1},"children":[{"type":"element","tag":"span","props":{"style":"--shiki-default:#24292EFF;--shiki-dark:#B392F0"},"children":[{"type":"text","value":"<"}]},{"type":"element","tag":"span","props":{"style":"--shiki-default:#22863A;--shiki-dark:#FFAB70"},"children":[{"type":"text","value":"z-grid"}]},{"type":"element","tag":"span","props":{"style":"--shiki-default:#24292EFF;--shiki-dark:#B392F0"},"children":[{"type":"text","value":">\n"}]}]},{"type":"element","tag":"span","props":{"class":"line","line":2},"children":[{"type":"element","tag":"span","props":{"style":"--shiki-default:#24292EFF;--shiki-dark:#B392F0"},"children":[{"type":"text","value":"   <"}]},{"type":"element","tag":"span","props":{"style":"--shiki-default:#22863A;--shiki-dark:#FFAB70"},"children":[{"type":"text","value":"z-grid-item"}]},{"type":"element","tag":"span","props":{"style":"--shiki-default:#6F42C1;--shiki-dark:#B392F0"},"children":[{"type":"text","value":" v-for"}]},{"type":"element","tag":"span","props":{"style":"--shiki-default:#D32F2F;--shiki-dark:#F97583"},"children":[{"type":"text","value":"="}]},{"type":"element","tag":"span","props":{"style":"--shiki-default:#22863A;--shiki-dark:#FFAB70"},"children":[{"type":"text","value":"\"i in 4\""}]},{"type":"element","tag":"span","props":{"style":"--shiki-default:#6F42C1;--shiki-dark:#B392F0"},"children":[{"type":"text","value":" :key"}]},{"type":"element","tag":"span","props":{"style":"--shiki-default:#D32F2F;--shiki-dark:#F97583"},"children":[{"type":"text","value":"="}]},{"type":"element","tag":"span","props":{"style":"--shiki-default:#22863A;--shiki-dark:#FFAB70"},"children":[{"type":"text","value":"\"i\""}]},{"type":"element","tag":"span","props":{"style":"--shiki-default:#6F42C1;--shiki-dark:#B392F0"},"children":[{"type":"text","value":" icon"}]},{"type":"element","tag":"span","props":{"style":"--shiki-default:#D32F2F;--shiki-dark:#F97583"},"children":[{"type":"text","value":"="}]},{"type":"element","tag":"span","props":{"style":"--shiki-default:#22863A;--shiki-dark:#FFAB70"},"children":[{"type":"text","value":"\"image\""}]},{"type":"element","tag":"span","props":{"style":"--shiki-default:#6F42C1;--shiki-dark:#B392F0"},"children":[{"type":"text","value":" text"}]},{"type":"element","tag":"span","props":{"style":"--shiki-default:#D32F2F;--shiki-dark:#F97583"},"children":[{"type":"text","value":"="}]},{"type":"element","tag":"span","props":{"style":"--shiki-default:#22863A;--shiki-dark:#FFAB70"},"children":[{"type":"text","value":"\"text\""}]},{"type":"element","tag":"span","props":{"style":"--shiki-default:#24292EFF;--shiki-dark:#B392F0"},"children":[{"type":"text","value":" />\n"}]}]},{"type":"element","tag":"span","props":{"class":"line","line":3},"children":[{"type":"element","tag":"span","props":{"style":"--shiki-default:#24292EFF;--shiki-dark:#B392F0"},"children":[{"type":"text","value":"</"}]},{"type":"element","tag":"span","props":{"style":"--shiki-default:#22863A;--shiki-dark:#FFAB70"},"children":[{"type":"text","value":"z-grid"}]},{"type":"element","tag":"span","props":{"style":"--shiki-default:#24292EFF;--shiki-dark:#B392F0"},"children":[{"type":"text","value":">\n"}]}]}]}]},{"type":"element","tag":"h3","props":{"id":"customize-the-number-of-columns"},"children":[{"type":"text","value":"Customize the number of columns"}]},{"type":"element","tag":"p","props":{},"children":[{"type":"text","value":"By default, four grids are displayed in one row, and the number of columns can be customized through "},{"type":"element","tag":"code","props":{"className":[]},"children":[{"type":"text","value":"column-num"}]},{"type":"text","value":"."}]},{"type":"element","tag":"pre","props":{"className":"language-html shiki shiki-themes min-light min-dark","code":"<z-grid :column-num=\"3\">\n   <z-grid-item v-for=\"i in 6\" :key=\"i\" icon=\"image\" text=\"text\" />\n</z-grid>\n","language":"html","meta":"","style":""},"children":[{"type":"element","tag":"code","props":{"__ignoreMap":""},"children":[{"type":"element","tag":"span","props":{"class":"line","line":1},"children":[{"type":"element","tag":"span","props":{"style":"--shiki-default:#24292EFF;--shiki-dark:#B392F0"},"children":[{"type":"text","value":"<"}]},{"type":"element","tag":"span","props":{"style":"--shiki-default:#22863A;--shiki-dark:#FFAB70"},"children":[{"type":"text","value":"z-grid"}]},{"type":"element","tag":"span","props":{"style":"--shiki-default:#6F42C1;--shiki-dark:#B392F0"},"children":[{"type":"text","value":" :column-num"}]},{"type":"element","tag":"span","props":{"style":"--shiki-default:#D32F2F;--shiki-dark:#F97583"},"children":[{"type":"text","value":"="}]},{"type":"element","tag":"span","props":{"style":"--shiki-default:#22863A;--shiki-dark:#FFAB70"},"children":[{"type":"text","value":"\"3\""}]},{"type":"element","tag":"span","props":{"style":"--shiki-default:#24292EFF;--shiki-dark:#B392F0"},"children":[{"type":"text","value":">\n"}]}]},{"type":"element","tag":"span","props":{"class":"line","line":2},"children":[{"type":"element","tag":"span","props":{"style":"--shiki-default:#24292EFF;--shiki-dark:#B392F0"},"children":[{"type":"text","value":"   <"}]},{"type":"element","tag":"span","props":{"style":"--shiki-default:#22863A;--shiki-dark:#FFAB70"},"children":[{"type":"text","value":"z-grid-item"}]},{"type":"element","tag":"span","props":{"style":"--shiki-default:#6F42C1;--shiki-dark:#B392F0"},"children":[{"type":"text","value":" v-for"}]},{"type":"element","tag":"span","props":{"style":"--shiki-default:#D32F2F;--shiki-dark:#F97583"},"children":[{"type":"text","value":"="}]},{"type":"element","tag":"span","props":{"style":"--shiki-default:#22863A;--shiki-dark:#FFAB70"},"children":[{"type":"text","value":"\"i in 6\""}]},{"type":"element","tag":"span","props":{"style":"--shiki-default:#6F42C1;--shiki-dark:#B392F0"},"children":[{"type":"text","value":" :key"}]},{"type":"element","tag":"span","props":{"style":"--shiki-default:#D32F2F;--shiki-dark:#F97583"},"children":[{"type":"text","value":"="}]},{"type":"element","tag":"span","props":{"style":"--shiki-default:#22863A;--shiki-dark:#FFAB70"},"children":[{"type":"text","value":"\"i\""}]},{"type":"element","tag":"span","props":{"style":"--shiki-default:#6F42C1;--shiki-dark:#B392F0"},"children":[{"type":"text","value":" icon"}]},{"type":"element","tag":"span","props":{"style":"--shiki-default:#D32F2F;--shiki-dark:#F97583"},"children":[{"type":"text","value":"="}]},{"type":"element","tag":"span","props":{"style":"--shiki-default:#22863A;--shiki-dark:#FFAB70"},"children":[{"type":"text","value":"\"image\""}]},{"type":"element","tag":"span","props":{"style":"--shiki-default:#6F42C1;--shiki-dark:#B392F0"},"children":[{"type":"text","value":" text"}]},{"type":"element","tag":"span","props":{"style":"--shiki-default:#D32F2F;--shiki-dark:#F97583"},"children":[{"type":"text","value":"="}]},{"type":"element","tag":"span","props":{"style":"--shiki-default:#22863A;--shiki-dark:#FFAB70"},"children":[{"type":"text","value":"\"text\""}]},{"type":"element","tag":"span","props":{"style":"--shiki-default:#24292EFF;--shiki-dark:#B392F0"},"children":[{"type":"text","value":" />\n"}]}]},{"type":"element","tag":"span","props":{"class":"line","line":3},"children":[{"type":"element","tag":"span","props":{"style":"--shiki-default:#24292EFF;--shiki-dark:#B392F0"},"children":[{"type":"text","value":"</"}]},{"type":"element","tag":"span","props":{"style":"--shiki-default:#22863A;--shiki-dark:#FFAB70"},"children":[{"type":"text","value":"z-grid"}]},{"type":"element","tag":"span","props":{"style":"--shiki-default:#24292EFF;--shiki-dark:#B392F0"},"children":[{"type":"text","value":">\n"}]}]}]}]},{"type":"element","tag":"h3","props":{"id":"custom-content"},"children":[{"type":"text","value":"Custom content"}]},{"type":"element","tag":"p","props":{},"children":[{"type":"text","value":"The content displayed in the grid can be customized through slots."}]},{"type":"element","tag":"pre","props":{"className":"language-html shiki shiki-themes min-light min-dark","code":"<z-grid :border=\"false\" :column-num=\"3\">\n   <z-grid-item>\n     <z-image\n       mode=\"widthFix\"\n       src=\"https://cdn.zebraui.com/zebra-ui/images/swipe-demo/swipe1.jpg\"\n     />\n   </z-grid-item>\n   <z-grid-item>\n     <z-image\n       mode=\"widthFix\"\n       src=\"https://cdn.zebraui.com/zebra-ui/images/swipe-demo/swipe2.jpg\"\n     />\n   </z-grid-item>\n   <z-grid-item>\n     <z-image\n       mode=\"widthFix\"\n       src=\"https://cdn.zebraui.com/zebra-ui/images/swipe-demo/swipe3.jpg\"\n     />\n   </z-grid-item>\n</z-grid>\n","language":"html","meta":"","style":""},"children":[{"type":"element","tag":"code","props":{"__ignoreMap":""},"children":[{"type":"element","tag":"span","props":{"class":"line","line":1},"children":[{"type":"element","tag":"span","props":{"style":"--shiki-default:#24292EFF;--shiki-dark:#B392F0"},"children":[{"type":"text","value":"<"}]},{"type":"element","tag":"span","props":{"style":"--shiki-default:#22863A;--shiki-dark:#FFAB70"},"children":[{"type":"text","value":"z-grid"}]},{"type":"element","tag":"span","props":{"style":"--shiki-default:#6F42C1;--shiki-dark:#B392F0"},"children":[{"type":"text","value":" :border"}]},{"type":"element","tag":"span","props":{"style":"--shiki-default:#D32F2F;--shiki-dark:#F97583"},"children":[{"type":"text","value":"="}]},{"type":"element","tag":"span","props":{"style":"--shiki-default:#22863A;--shiki-dark:#FFAB70"},"children":[{"type":"text","value":"\"false\""}]},{"type":"element","tag":"span","props":{"style":"--shiki-default:#6F42C1;--shiki-dark:#B392F0"},"children":[{"type":"text","value":" :column-num"}]},{"type":"element","tag":"span","props":{"style":"--shiki-default:#D32F2F;--shiki-dark:#F97583"},"children":[{"type":"text","value":"="}]},{"type":"element","tag":"span","props":{"style":"--shiki-default:#22863A;--shiki-dark:#FFAB70"},"children":[{"type":"text","value":"\"3\""}]},{"type":"element","tag":"span","props":{"style":"--shiki-default:#24292EFF;--shiki-dark:#B392F0"},"children":[{"type":"text","value":">\n"}]}]},{"type":"element","tag":"span","props":{"class":"line","line":2},"children":[{"type":"element","tag":"span","props":{"style":"--shiki-default:#24292EFF;--shiki-dark:#B392F0"},"children":[{"type":"text","value":"   <"}]},{"type":"element","tag":"span","props":{"style":"--shiki-default:#22863A;--shiki-dark:#FFAB70"},"children":[{"type":"text","value":"z-grid-item"}]},{"type":"element","tag":"span","props":{"style":"--shiki-default:#24292EFF;--shiki-dark:#B392F0"},"children":[{"type":"text","value":">\n"}]}]},{"type":"element","tag":"span","props":{"class":"line","line":3},"children":[{"type":"element","tag":"span","props":{"style":"--shiki-default:#24292EFF;--shiki-dark:#B392F0"},"children":[{"type":"text","value":"     <"}]},{"type":"element","tag":"span","props":{"style":"--shiki-default:#22863A;--shiki-dark:#FFAB70"},"children":[{"type":"text","value":"z-image\n"}]}]},{"type":"element","tag":"span","props":{"class":"line","line":4},"children":[{"type":"element","tag":"span","props":{"style":"--shiki-default:#6F42C1;--shiki-dark:#B392F0"},"children":[{"type":"text","value":"       mode"}]},{"type":"element","tag":"span","props":{"style":"--shiki-default:#D32F2F;--shiki-dark:#F97583"},"children":[{"type":"text","value":"="}]},{"type":"element","tag":"span","props":{"style":"--shiki-default:#22863A;--shiki-dark:#FFAB70"},"children":[{"type":"text","value":"\"widthFix\"\n"}]}]},{"type":"element","tag":"span","props":{"class":"line","line":5},"children":[{"type":"element","tag":"span","props":{"style":"--shiki-default:#6F42C1;--shiki-dark:#B392F0"},"children":[{"type":"text","value":"       src"}]},{"type":"element","tag":"span","props":{"style":"--shiki-default:#D32F2F;--shiki-dark:#F97583"},"children":[{"type":"text","value":"="}]},{"type":"element","tag":"span","props":{"style":"--shiki-default:#22863A;--shiki-dark:#FFAB70"},"children":[{"type":"text","value":"\"https://cdn.zebraui.com/zebra-ui/images/swipe-demo/swipe1.jpg\"\n"}]}]},{"type":"element","tag":"span","props":{"class":"line","line":6},"children":[{"type":"element","tag":"span","props":{"style":"--shiki-default:#24292EFF;--shiki-dark:#B392F0"},"children":[{"type":"text","value":"     />\n"}]}]},{"type":"element","tag":"span","props":{"class":"line","line":7},"children":[{"type":"element","tag":"span","props":{"style":"--shiki-default:#24292EFF;--shiki-dark:#B392F0"},"children":[{"type":"text","value":"   </"}]},{"type":"element","tag":"span","props":{"style":"--shiki-default:#22863A;--shiki-dark:#FFAB70"},"children":[{"type":"text","value":"z-grid-item"}]},{"type":"element","tag":"span","props":{"style":"--shiki-default:#24292EFF;--shiki-dark:#B392F0"},"children":[{"type":"text","value":">\n"}]}]},{"type":"element","tag":"span","props":{"class":"line","line":8},"children":[{"type":"element","tag":"span","props":{"style":"--shiki-default:#24292EFF;--shiki-dark:#B392F0"},"children":[{"type":"text","value":"   <"}]},{"type":"element","tag":"span","props":{"style":"--shiki-default:#22863A;--shiki-dark:#FFAB70"},"children":[{"type":"text","value":"z-grid-item"}]},{"type":"element","tag":"span","props":{"style":"--shiki-default:#24292EFF;--shiki-dark:#B392F0"},"children":[{"type":"text","value":">\n"}]}]},{"type":"element","tag":"span","props":{"class":"line","line":9},"children":[{"type":"element","tag":"span","props":{"style":"--shiki-default:#24292EFF;--shiki-dark:#B392F0"},"children":[{"type":"text","value":"     <"}]},{"type":"element","tag":"span","props":{"style":"--shiki-default:#22863A;--shiki-dark:#FFAB70"},"children":[{"type":"text","value":"z-image\n"}]}]},{"type":"element","tag":"span","props":{"class":"line","line":10},"children":[{"type":"element","tag":"span","props":{"style":"--shiki-default:#6F42C1;--shiki-dark:#B392F0"},"children":[{"type":"text","value":"       mode"}]},{"type":"element","tag":"span","props":{"style":"--shiki-default:#D32F2F;--shiki-dark:#F97583"},"children":[{"type":"text","value":"="}]},{"type":"element","tag":"span","props":{"style":"--shiki-default:#22863A;--shiki-dark:#FFAB70"},"children":[{"type":"text","value":"\"widthFix\"\n"}]}]},{"type":"element","tag":"span","props":{"class":"line","line":11},"children":[{"type":"element","tag":"span","props":{"style":"--shiki-default:#6F42C1;--shiki-dark:#B392F0"},"children":[{"type":"text","value":"       src"}]},{"type":"element","tag":"span","props":{"style":"--shiki-default:#D32F2F;--shiki-dark:#F97583"},"children":[{"type":"text","value":"="}]},{"type":"element","tag":"span","props":{"style":"--shiki-default:#22863A;--shiki-dark:#FFAB70"},"children":[{"type":"text","value":"\"https://cdn.zebraui.com/zebra-ui/images/swipe-demo/swipe2.jpg\"\n"}]}]},{"type":"element","tag":"span","props":{"class":"line","line":12},"children":[{"type":"element","tag":"span","props":{"style":"--shiki-default:#24292EFF;--shiki-dark:#B392F0"},"children":[{"type":"text","value":"     />\n"}]}]},{"type":"element","tag":"span","props":{"class":"line","line":13},"children":[{"type":"element","tag":"span","props":{"style":"--shiki-default:#24292EFF;--shiki-dark:#B392F0"},"children":[{"type":"text","value":"   </"}]},{"type":"element","tag":"span","props":{"style":"--shiki-default:#22863A;--shiki-dark:#FFAB70"},"children":[{"type":"text","value":"z-grid-item"}]},{"type":"element","tag":"span","props":{"style":"--shiki-default:#24292EFF;--shiki-dark:#B392F0"},"children":[{"type":"text","value":">\n"}]}]},{"type":"element","tag":"span","props":{"class":"line","line":14},"children":[{"type":"element","tag":"span","props":{"style":"--shiki-default:#24292EFF;--shiki-dark:#B392F0"},"children":[{"type":"text","value":"   <"}]},{"type":"element","tag":"span","props":{"style":"--shiki-default:#22863A;--shiki-dark:#FFAB70"},"children":[{"type":"text","value":"z-grid-item"}]},{"type":"element","tag":"span","props":{"style":"--shiki-default:#24292EFF;--shiki-dark:#B392F0"},"children":[{"type":"text","value":">\n"}]}]},{"type":"element","tag":"span","props":{"class":"line","line":15},"children":[{"type":"element","tag":"span","props":{"style":"--shiki-default:#24292EFF;--shiki-dark:#B392F0"},"children":[{"type":"text","value":"     <"}]},{"type":"element","tag":"span","props":{"style":"--shiki-default:#22863A;--shiki-dark:#FFAB70"},"children":[{"type":"text","value":"z-image\n"}]}]},{"type":"element","tag":"span","props":{"class":"line","line":16},"children":[{"type":"element","tag":"span","props":{"style":"--shiki-default:#6F42C1;--shiki-dark:#B392F0"},"children":[{"type":"text","value":"       mode"}]},{"type":"element","tag":"span","props":{"style":"--shiki-default:#D32F2F;--shiki-dark:#F97583"},"children":[{"type":"text","value":"="}]},{"type":"element","tag":"span","props":{"style":"--shiki-default:#22863A;--shiki-dark:#FFAB70"},"children":[{"type":"text","value":"\"widthFix\"\n"}]}]},{"type":"element","tag":"span","props":{"class":"line","line":17},"children":[{"type":"element","tag":"span","props":{"style":"--shiki-default:#6F42C1;--shiki-dark:#B392F0"},"children":[{"type":"text","value":"       src"}]},{"type":"element","tag":"span","props":{"style":"--shiki-default:#D32F2F;--shiki-dark:#F97583"},"children":[{"type":"text","value":"="}]},{"type":"element","tag":"span","props":{"style":"--shiki-default:#22863A;--shiki-dark:#FFAB70"},"children":[{"type":"text","value":"\"https://cdn.zebraui.com/zebra-ui/images/swipe-demo/swipe3.jpg\"\n"}]}]},{"type":"element","tag":"span","props":{"class":"line","line":18},"children":[{"type":"element","tag":"span","props":{"style":"--shiki-default:#24292EFF;--shiki-dark:#B392F0"},"children":[{"type":"text","value":"     />\n"}]}]},{"type":"element","tag":"span","props":{"class":"line","line":19},"children":[{"type":"element","tag":"span","props":{"style":"--shiki-default:#24292EFF;--shiki-dark:#B392F0"},"children":[{"type":"text","value":"   </"}]},{"type":"element","tag":"span","props":{"style":"--shiki-default:#22863A;--shiki-dark:#FFAB70"},"children":[{"type":"text","value":"z-grid-item"}]},{"type":"element","tag":"span","props":{"style":"--shiki-default:#24292EFF;--shiki-dark:#B392F0"},"children":[{"type":"text","value":">\n"}]}]},{"type":"element","tag":"span","props":{"class":"line","line":20},"children":[{"type":"element","tag":"span","props":{"style":"--shiki-default:#24292EFF;--shiki-dark:#B392F0"},"children":[{"type":"text","value":"</"}]},{"type":"element","tag":"span","props":{"style":"--shiki-default:#22863A;--shiki-dark:#FFAB70"},"children":[{"type":"text","value":"z-grid"}]},{"type":"element","tag":"span","props":{"style":"--shiki-default:#24292EFF;--shiki-dark:#B392F0"},"children":[{"type":"text","value":">\n"}]}]}]}]},{"type":"element","tag":"h3","props":{"id":"square-grid"},"children":[{"type":"text","value":"Square grid"}]},{"type":"element","tag":"p","props":{},"children":[{"type":"text","value":"After setting the "},{"type":"element","tag":"code","props":{"className":[]},"children":[{"type":"text","value":"square"}]},{"type":"text","value":" property, the height of the grid will be consistent with the width."}]},{"type":"element","tag":"pre","props":{"className":"language-html shiki shiki-themes min-light min-dark","code":"<z-grid square>\n   <z-grid-item v-for=\"i in 8\" :key=\"i\" icon=\"image\" text=\"text\" />\n</z-grid>\n","language":"html","meta":"","style":""},"children":[{"type":"element","tag":"code","props":{"__ignoreMap":""},"children":[{"type":"element","tag":"span","props":{"class":"line","line":1},"children":[{"type":"element","tag":"span","props":{"style":"--shiki-default:#24292EFF;--shiki-dark:#B392F0"},"children":[{"type":"text","value":"<"}]},{"type":"element","tag":"span","props":{"style":"--shiki-default:#22863A;--shiki-dark:#FFAB70"},"children":[{"type":"text","value":"z-grid"}]},{"type":"element","tag":"span","props":{"style":"--shiki-default:#6F42C1;--shiki-dark:#B392F0"},"children":[{"type":"text","value":" square"}]},{"type":"element","tag":"span","props":{"style":"--shiki-default:#24292EFF;--shiki-dark:#B392F0"},"children":[{"type":"text","value":">\n"}]}]},{"type":"element","tag":"span","props":{"class":"line","line":2},"children":[{"type":"element","tag":"span","props":{"style":"--shiki-default:#24292EFF;--shiki-dark:#B392F0"},"children":[{"type":"text","value":"   <"}]},{"type":"element","tag":"span","props":{"style":"--shiki-default:#22863A;--shiki-dark:#FFAB70"},"children":[{"type":"text","value":"z-grid-item"}]},{"type":"element","tag":"span","props":{"style":"--shiki-default:#6F42C1;--shiki-dark:#B392F0"},"children":[{"type":"text","value":" v-for"}]},{"type":"element","tag":"span","props":{"style":"--shiki-default:#D32F2F;--shiki-dark:#F97583"},"children":[{"type":"text","value":"="}]},{"type":"element","tag":"span","props":{"style":"--shiki-default:#22863A;--shiki-dark:#FFAB70"},"children":[{"type":"text","value":"\"i in 8\""}]},{"type":"element","tag":"span","props":{"style":"--shiki-default:#6F42C1;--shiki-dark:#B392F0"},"children":[{"type":"text","value":" :key"}]},{"type":"element","tag":"span","props":{"style":"--shiki-default:#D32F2F;--shiki-dark:#F97583"},"children":[{"type":"text","value":"="}]},{"type":"element","tag":"span","props":{"style":"--shiki-default:#22863A;--shiki-dark:#FFAB70"},"children":[{"type":"text","value":"\"i\""}]},{"type":"element","tag":"span","props":{"style":"--shiki-default:#6F42C1;--shiki-dark:#B392F0"},"children":[{"type":"text","value":" icon"}]},{"type":"element","tag":"span","props":{"style":"--shiki-default:#D32F2F;--shiki-dark:#F97583"},"children":[{"type":"text","value":"="}]},{"type":"element","tag":"span","props":{"style":"--shiki-default:#22863A;--shiki-dark:#FFAB70"},"children":[{"type":"text","value":"\"image\""}]},{"type":"element","tag":"span","props":{"style":"--shiki-default:#6F42C1;--shiki-dark:#B392F0"},"children":[{"type":"text","value":" text"}]},{"type":"element","tag":"span","props":{"style":"--shiki-default:#D32F2F;--shiki-dark:#F97583"},"children":[{"type":"text","value":"="}]},{"type":"element","tag":"span","props":{"style":"--shiki-default:#22863A;--shiki-dark:#FFAB70"},"children":[{"type":"text","value":"\"text\""}]},{"type":"element","tag":"span","props":{"style":"--shiki-default:#24292EFF;--shiki-dark:#B392F0"},"children":[{"type":"text","value":" />\n"}]}]},{"type":"element","tag":"span","props":{"class":"line","line":3},"children":[{"type":"element","tag":"span","props":{"style":"--shiki-default:#24292EFF;--shiki-dark:#B392F0"},"children":[{"type":"text","value":"</"}]},{"type":"element","tag":"span","props":{"style":"--shiki-default:#22863A;--shiki-dark:#FFAB70"},"children":[{"type":"text","value":"z-grid"}]},{"type":"element","tag":"span","props":{"style":"--shiki-default:#24292EFF;--shiki-dark:#B392F0"},"children":[{"type":"text","value":">\n"}]}]}]}]},{"type":"element","tag":"h3","props":{"id":"grid-spacing"},"children":[{"type":"text","value":"Grid spacing"}]},{"type":"element","tag":"p","props":{},"children":[{"type":"text","value":"Set the distance between grids through the "},{"type":"element","tag":"code","props":{"className":[]},"children":[{"type":"text","value":"gutter"}]},{"type":"text","value":" property."}]},{"type":"element","tag":"pre","props":{"className":"language-html shiki shiki-themes min-light min-dark","code":"<z-grid :gutter=\"10\">\n   <z-grid-item v-for=\"i in 8\" :key=\"i\" icon=\"image\" text=\"text\" />\n</z-grid>\n","language":"html","meta":"","style":""},"children":[{"type":"element","tag":"code","props":{"__ignoreMap":""},"children":[{"type":"element","tag":"span","props":{"class":"line","line":1},"children":[{"type":"element","tag":"span","props":{"style":"--shiki-default:#24292EFF;--shiki-dark:#B392F0"},"children":[{"type":"text","value":"<"}]},{"type":"element","tag":"span","props":{"style":"--shiki-default:#22863A;--shiki-dark:#FFAB70"},"children":[{"type":"text","value":"z-grid"}]},{"type":"element","tag":"span","props":{"style":"--shiki-default:#6F42C1;--shiki-dark:#B392F0"},"children":[{"type":"text","value":" :gutter"}]},{"type":"element","tag":"span","props":{"style":"--shiki-default:#D32F2F;--shiki-dark:#F97583"},"children":[{"type":"text","value":"="}]},{"type":"element","tag":"span","props":{"style":"--shiki-default:#22863A;--shiki-dark:#FFAB70"},"children":[{"type":"text","value":"\"10\""}]},{"type":"element","tag":"span","props":{"style":"--shiki-default:#24292EFF;--shiki-dark:#B392F0"},"children":[{"type":"text","value":">\n"}]}]},{"type":"element","tag":"span","props":{"class":"line","line":2},"children":[{"type":"element","tag":"span","props":{"style":"--shiki-default:#24292EFF;--shiki-dark:#B392F0"},"children":[{"type":"text","value":"   <"}]},{"type":"element","tag":"span","props":{"style":"--shiki-default:#22863A;--shiki-dark:#FFAB70"},"children":[{"type":"text","value":"z-grid-item"}]},{"type":"element","tag":"span","props":{"style":"--shiki-default:#6F42C1;--shiki-dark:#B392F0"},"children":[{"type":"text","value":" v-for"}]},{"type":"element","tag":"span","props":{"style":"--shiki-default:#D32F2F;--shiki-dark:#F97583"},"children":[{"type":"text","value":"="}]},{"type":"element","tag":"span","props":{"style":"--shiki-default:#22863A;--shiki-dark:#FFAB70"},"children":[{"type":"text","value":"\"i in 8\""}]},{"type":"element","tag":"span","props":{"style":"--shiki-default:#6F42C1;--shiki-dark:#B392F0"},"children":[{"type":"text","value":" :key"}]},{"type":"element","tag":"span","props":{"style":"--shiki-default:#D32F2F;--shiki-dark:#F97583"},"children":[{"type":"text","value":"="}]},{"type":"element","tag":"span","props":{"style":"--shiki-default:#22863A;--shiki-dark:#FFAB70"},"children":[{"type":"text","value":"\"i\""}]},{"type":"element","tag":"span","props":{"style":"--shiki-default:#6F42C1;--shiki-dark:#B392F0"},"children":[{"type":"text","value":" icon"}]},{"type":"element","tag":"span","props":{"style":"--shiki-default:#D32F2F;--shiki-dark:#F97583"},"children":[{"type":"text","value":"="}]},{"type":"element","tag":"span","props":{"style":"--shiki-default:#22863A;--shiki-dark:#FFAB70"},"children":[{"type":"text","value":"\"image\""}]},{"type":"element","tag":"span","props":{"style":"--shiki-default:#6F42C1;--shiki-dark:#B392F0"},"children":[{"type":"text","value":" text"}]},{"type":"element","tag":"span","props":{"style":"--shiki-default:#D32F2F;--shiki-dark:#F97583"},"children":[{"type":"text","value":"="}]},{"type":"element","tag":"span","props":{"style":"--shiki-default:#22863A;--shiki-dark:#FFAB70"},"children":[{"type":"text","value":"\"text\""}]},{"type":"element","tag":"span","props":{"style":"--shiki-default:#24292EFF;--shiki-dark:#B392F0"},"children":[{"type":"text","value":" />\n"}]}]},{"type":"element","tag":"span","props":{"class":"line","line":3},"children":[{"type":"element","tag":"span","props":{"style":"--shiki-default:#24292EFF;--shiki-dark:#B392F0"},"children":[{"type":"text","value":"</"}]},{"type":"element","tag":"span","props":{"style":"--shiki-default:#22863A;--shiki-dark:#FFAB70"},"children":[{"type":"text","value":"z-grid"}]},{"type":"element","tag":"span","props":{"style":"--shiki-default:#24292EFF;--shiki-dark:#B392F0"},"children":[{"type":"text","value":">\n"}]}]}]}]},{"type":"element","tag":"h3","props":{"id":"contents-arranged-horizontally"},"children":[{"type":"text","value":"Contents arranged horizontally"}]},{"type":"element","tag":"p","props":{},"children":[{"type":"text","value":"Set the "},{"type":"element","tag":"code","props":{"className":[]},"children":[{"type":"text","value":"direction"}]},{"type":"text","value":" attribute to "},{"type":"element","tag":"code","props":{"className":[]},"children":[{"type":"text","value":"horizontal"}]},{"type":"text","value":" to arrange the contents of the grid horizontally."}]},{"type":"element","tag":"pre","props":{"className":"language-html shiki shiki-themes min-light min-dark","code":"<z-grid direction=\"horizontal\" :column-num=\"3\">\n   <z-grid-item icon=\"image\" text=\"text\" />\n   <z-grid-item icon=\"image\" text=\"text\" />\n   <z-grid-item icon=\"image\" text=\"text\" />\n</z-grid>\n","language":"html","meta":"","style":""},"children":[{"type":"element","tag":"code","props":{"__ignoreMap":""},"children":[{"type":"element","tag":"span","props":{"class":"line","line":1},"children":[{"type":"element","tag":"span","props":{"style":"--shiki-default:#24292EFF;--shiki-dark:#B392F0"},"children":[{"type":"text","value":"<"}]},{"type":"element","tag":"span","props":{"style":"--shiki-default:#22863A;--shiki-dark:#FFAB70"},"children":[{"type":"text","value":"z-grid"}]},{"type":"element","tag":"span","props":{"style":"--shiki-default:#6F42C1;--shiki-dark:#B392F0"},"children":[{"type":"text","value":" direction"}]},{"type":"element","tag":"span","props":{"style":"--shiki-default:#D32F2F;--shiki-dark:#F97583"},"children":[{"type":"text","value":"="}]},{"type":"element","tag":"span","props":{"style":"--shiki-default:#22863A;--shiki-dark:#FFAB70"},"children":[{"type":"text","value":"\"horizontal\""}]},{"type":"element","tag":"span","props":{"style":"--shiki-default:#6F42C1;--shiki-dark:#B392F0"},"children":[{"type":"text","value":" :column-num"}]},{"type":"element","tag":"span","props":{"style":"--shiki-default:#D32F2F;--shiki-dark:#F97583"},"children":[{"type":"text","value":"="}]},{"type":"element","tag":"span","props":{"style":"--shiki-default:#22863A;--shiki-dark:#FFAB70"},"children":[{"type":"text","value":"\"3\""}]},{"type":"element","tag":"span","props":{"style":"--shiki-default:#24292EFF;--shiki-dark:#B392F0"},"children":[{"type":"text","value":">\n"}]}]},{"type":"element","tag":"span","props":{"class":"line","line":2},"children":[{"type":"element","tag":"span","props":{"style":"--shiki-default:#24292EFF;--shiki-dark:#B392F0"},"children":[{"type":"text","value":"   <"}]},{"type":"element","tag":"span","props":{"style":"--shiki-default:#22863A;--shiki-dark:#FFAB70"},"children":[{"type":"text","value":"z-grid-item"}]},{"type":"element","tag":"span","props":{"style":"--shiki-default:#6F42C1;--shiki-dark:#B392F0"},"children":[{"type":"text","value":" icon"}]},{"type":"element","tag":"span","props":{"style":"--shiki-default:#D32F2F;--shiki-dark:#F97583"},"children":[{"type":"text","value":"="}]},{"type":"element","tag":"span","props":{"style":"--shiki-default:#22863A;--shiki-dark:#FFAB70"},"children":[{"type":"text","value":"\"image\""}]},{"type":"element","tag":"span","props":{"style":"--shiki-default:#6F42C1;--shiki-dark:#B392F0"},"children":[{"type":"text","value":" text"}]},{"type":"element","tag":"span","props":{"style":"--shiki-default:#D32F2F;--shiki-dark:#F97583"},"children":[{"type":"text","value":"="}]},{"type":"element","tag":"span","props":{"style":"--shiki-default:#22863A;--shiki-dark:#FFAB70"},"children":[{"type":"text","value":"\"text\""}]},{"type":"element","tag":"span","props":{"style":"--shiki-default:#24292EFF;--shiki-dark:#B392F0"},"children":[{"type":"text","value":" />\n"}]}]},{"type":"element","tag":"span","props":{"class":"line","line":3},"children":[{"type":"element","tag":"span","props":{"style":"--shiki-default:#24292EFF;--shiki-dark:#B392F0"},"children":[{"type":"text","value":"   <"}]},{"type":"element","tag":"span","props":{"style":"--shiki-default:#22863A;--shiki-dark:#FFAB70"},"children":[{"type":"text","value":"z-grid-item"}]},{"type":"element","tag":"span","props":{"style":"--shiki-default:#6F42C1;--shiki-dark:#B392F0"},"children":[{"type":"text","value":" icon"}]},{"type":"element","tag":"span","props":{"style":"--shiki-default:#D32F2F;--shiki-dark:#F97583"},"children":[{"type":"text","value":"="}]},{"type":"element","tag":"span","props":{"style":"--shiki-default:#22863A;--shiki-dark:#FFAB70"},"children":[{"type":"text","value":"\"image\""}]},{"type":"element","tag":"span","props":{"style":"--shiki-default:#6F42C1;--shiki-dark:#B392F0"},"children":[{"type":"text","value":" text"}]},{"type":"element","tag":"span","props":{"style":"--shiki-default:#D32F2F;--shiki-dark:#F97583"},"children":[{"type":"text","value":"="}]},{"type":"element","tag":"span","props":{"style":"--shiki-default:#22863A;--shiki-dark:#FFAB70"},"children":[{"type":"text","value":"\"text\""}]},{"type":"element","tag":"span","props":{"style":"--shiki-default:#24292EFF;--shiki-dark:#B392F0"},"children":[{"type":"text","value":" />\n"}]}]},{"type":"element","tag":"span","props":{"class":"line","line":4},"children":[{"type":"element","tag":"span","props":{"style":"--shiki-default:#24292EFF;--shiki-dark:#B392F0"},"children":[{"type":"text","value":"   <"}]},{"type":"element","tag":"span","props":{"style":"--shiki-default:#22863A;--shiki-dark:#FFAB70"},"children":[{"type":"text","value":"z-grid-item"}]},{"type":"element","tag":"span","props":{"style":"--shiki-default:#6F42C1;--shiki-dark:#B392F0"},"children":[{"type":"text","value":" icon"}]},{"type":"element","tag":"span","props":{"style":"--shiki-default:#D32F2F;--shiki-dark:#F97583"},"children":[{"type":"text","value":"="}]},{"type":"element","tag":"span","props":{"style":"--shiki-default:#22863A;--shiki-dark:#FFAB70"},"children":[{"type":"text","value":"\"image\""}]},{"type":"element","tag":"span","props":{"style":"--shiki-default:#6F42C1;--shiki-dark:#B392F0"},"children":[{"type":"text","value":" text"}]},{"type":"element","tag":"span","props":{"style":"--shiki-default:#D32F2F;--shiki-dark:#F97583"},"children":[{"type":"text","value":"="}]},{"type":"element","tag":"span","props":{"style":"--shiki-default:#22863A;--shiki-dark:#FFAB70"},"children":[{"type":"text","value":"\"text\""}]},{"type":"element","tag":"span","props":{"style":"--shiki-default:#24292EFF;--shiki-dark:#B392F0"},"children":[{"type":"text","value":" />\n"}]}]},{"type":"element","tag":"span","props":{"class":"line","line":5},"children":[{"type":"element","tag":"span","props":{"style":"--shiki-default:#24292EFF;--shiki-dark:#B392F0"},"children":[{"type":"text","value":"</"}]},{"type":"element","tag":"span","props":{"style":"--shiki-default:#22863A;--shiki-dark:#FFAB70"},"children":[{"type":"text","value":"z-grid"}]},{"type":"element","tag":"span","props":{"style":"--shiki-default:#24292EFF;--shiki-dark:#B392F0"},"children":[{"type":"text","value":">\n"}]}]}]}]},{"type":"element","tag":"h3","props":{"id":"logo-tips"},"children":[{"type":"text","value":"Logo Tips"}]},{"type":"element","tag":"p","props":{},"children":[{"type":"text","value":"After setting the "},{"type":"element","tag":"code","props":{"className":[]},"children":[{"type":"text","value":"dot"}]},{"type":"text","value":" attribute, a small red dot will be displayed in the upper right corner of the icon. After setting the "},{"type":"element","tag":"code","props":{"className":[]},"children":[{"type":"text","value":"badge"}]},{"type":"text","value":" attribute, the corresponding logo will be displayed in the upper right corner of the icon."}]},{"type":"element","tag":"pre","props":{"className":"language-html shiki shiki-themes min-light min-dark","code":"<z-grid :column-num=\"2\">\n   <z-grid-item icon=\"home\" text=\"text\" dot />\n   <z-grid-item icon=\"search\" text=\"text\" badge=\"99+\" />\n</z-grid>\n","language":"html","meta":"","style":""},"children":[{"type":"element","tag":"code","props":{"__ignoreMap":""},"children":[{"type":"element","tag":"span","props":{"class":"line","line":1},"children":[{"type":"element","tag":"span","props":{"style":"--shiki-default:#24292EFF;--shiki-dark:#B392F0"},"children":[{"type":"text","value":"<"}]},{"type":"element","tag":"span","props":{"style":"--shiki-default:#22863A;--shiki-dark:#FFAB70"},"children":[{"type":"text","value":"z-grid"}]},{"type":"element","tag":"span","props":{"style":"--shiki-default:#6F42C1;--shiki-dark:#B392F0"},"children":[{"type":"text","value":" :column-num"}]},{"type":"element","tag":"span","props":{"style":"--shiki-default:#D32F2F;--shiki-dark:#F97583"},"children":[{"type":"text","value":"="}]},{"type":"element","tag":"span","props":{"style":"--shiki-default:#22863A;--shiki-dark:#FFAB70"},"children":[{"type":"text","value":"\"2\""}]},{"type":"element","tag":"span","props":{"style":"--shiki-default:#24292EFF;--shiki-dark:#B392F0"},"children":[{"type":"text","value":">\n"}]}]},{"type":"element","tag":"span","props":{"class":"line","line":2},"children":[{"type":"element","tag":"span","props":{"style":"--shiki-default:#24292EFF;--shiki-dark:#B392F0"},"children":[{"type":"text","value":"   <"}]},{"type":"element","tag":"span","props":{"style":"--shiki-default:#22863A;--shiki-dark:#FFAB70"},"children":[{"type":"text","value":"z-grid-item"}]},{"type":"element","tag":"span","props":{"style":"--shiki-default:#6F42C1;--shiki-dark:#B392F0"},"children":[{"type":"text","value":" icon"}]},{"type":"element","tag":"span","props":{"style":"--shiki-default:#D32F2F;--shiki-dark:#F97583"},"children":[{"type":"text","value":"="}]},{"type":"element","tag":"span","props":{"style":"--shiki-default:#22863A;--shiki-dark:#FFAB70"},"children":[{"type":"text","value":"\"home\""}]},{"type":"element","tag":"span","props":{"style":"--shiki-default:#6F42C1;--shiki-dark:#B392F0"},"children":[{"type":"text","value":" text"}]},{"type":"element","tag":"span","props":{"style":"--shiki-default:#D32F2F;--shiki-dark:#F97583"},"children":[{"type":"text","value":"="}]},{"type":"element","tag":"span","props":{"style":"--shiki-default:#22863A;--shiki-dark:#FFAB70"},"children":[{"type":"text","value":"\"text\""}]},{"type":"element","tag":"span","props":{"style":"--shiki-default:#6F42C1;--shiki-dark:#B392F0"},"children":[{"type":"text","value":" dot"}]},{"type":"element","tag":"span","props":{"style":"--shiki-default:#24292EFF;--shiki-dark:#B392F0"},"children":[{"type":"text","value":" />\n"}]}]},{"type":"element","tag":"span","props":{"class":"line","line":3},"children":[{"type":"element","tag":"span","props":{"style":"--shiki-default:#24292EFF;--shiki-dark:#B392F0"},"children":[{"type":"text","value":"   <"}]},{"type":"element","tag":"span","props":{"style":"--shiki-default:#22863A;--shiki-dark:#FFAB70"},"children":[{"type":"text","value":"z-grid-item"}]},{"type":"element","tag":"span","props":{"style":"--shiki-default:#6F42C1;--shiki-dark:#B392F0"},"children":[{"type":"text","value":" icon"}]},{"type":"element","tag":"span","props":{"style":"--shiki-default:#D32F2F;--shiki-dark:#F97583"},"children":[{"type":"text","value":"="}]},{"type":"element","tag":"span","props":{"style":"--shiki-default:#22863A;--shiki-dark:#FFAB70"},"children":[{"type":"text","value":"\"search\""}]},{"type":"element","tag":"span","props":{"style":"--shiki-default:#6F42C1;--shiki-dark:#B392F0"},"children":[{"type":"text","value":" text"}]},{"type":"element","tag":"span","props":{"style":"--shiki-default:#D32F2F;--shiki-dark:#F97583"},"children":[{"type":"text","value":"="}]},{"type":"element","tag":"span","props":{"style":"--shiki-default:#22863A;--shiki-dark:#FFAB70"},"children":[{"type":"text","value":"\"text\""}]},{"type":"element","tag":"span","props":{"style":"--shiki-default:#6F42C1;--shiki-dark:#B392F0"},"children":[{"type":"text","value":" badge"}]},{"type":"element","tag":"span","props":{"style":"--shiki-default:#D32F2F;--shiki-dark:#F97583"},"children":[{"type":"text","value":"="}]},{"type":"element","tag":"span","props":{"style":"--shiki-default:#22863A;--shiki-dark:#FFAB70"},"children":[{"type":"text","value":"\"99+\""}]},{"type":"element","tag":"span","props":{"style":"--shiki-default:#24292EFF;--shiki-dark:#B392F0"},"children":[{"type":"text","value":" />\n"}]}]},{"type":"element","tag":"span","props":{"class":"line","line":4},"children":[{"type":"element","tag":"span","props":{"style":"--shiki-default:#24292EFF;--shiki-dark:#B392F0"},"children":[{"type":"text","value":"</"}]},{"type":"element","tag":"span","props":{"style":"--shiki-default:#22863A;--shiki-dark:#FFAB70"},"children":[{"type":"text","value":"z-grid"}]},{"type":"element","tag":"span","props":{"style":"--shiki-default:#24292EFF;--shiki-dark:#B392F0"},"children":[{"type":"text","value":">\n"}]}]}]}]},{"type":"element","tag":"h2","props":{"id":"api"},"children":[{"type":"text","value":"API"}]},{"type":"element","tag":"h3","props":{"id":"grid-props"},"children":[{"type":"text","value":"Grid Props"}]},{"type":"text","value":"\n\n\n\n\n\n\n\n\n\n\n\n\n\n\n\n\n\n\n\n\n\n\n\n\n\n\n\n\n\n\n\n\n\n\n\n\n\n\n\n\n\n\n\n\n\n\n\n\n\n\n\n\n\n\n\n\n\n\n\n\n\n\n\n\n\n"},{"type":"element","tag":"table","props":{},"children":[{"type":"element","tag":"thead","props":{},"children":[{"type":"element","tag":"tr","props":{},"children":[{"type":"element","tag":"th","props":{},"children":[{"type":"text","value":"Parameters"}]},{"type":"element","tag":"th","props":{},"children":[{"type":"text","value":"Description"}]},{"type":"element","tag":"th","props":{},"children":[{"type":"text","value":"Type"}]},{"type":"element","tag":"th","props":{},"children":[{"type":"text","value":"Default value"}]}]}]},{"type":"element","tag":"tbody","props":{},"children":[{"type":"element","tag":"tr","props":{},"children":[{"type":"element","tag":"td","props":{},"children":[{"type":"text","value":"column-num"}]},{"type":"element","tag":"td","props":{},"children":[{"type":"text","value":"column number"}]},{"type":"element","tag":"td","props":{},"children":[{"type":"element","tag":"em","props":{},"children":[{"type":"text","value":"number | string"}]}]},{"type":"element","tag":"td","props":{},"children":[{"type":"element","tag":"code","props":{"className":[]},"children":[{"type":"text","value":"4"}]}]}]},{"type":"element","tag":"tr","props":{},"children":[{"type":"element","tag":"td","props":{},"children":[{"type":"text","value":"icon-size"}]},{"type":"element","tag":"td","props":{},"children":[{"type":"text","value":"Icon size, default unit is "},{"type":"element","tag":"code","props":{"className":[]},"children":[{"type":"text","value":"px"}]}]},{"type":"element","tag":"td","props":{},"children":[{"type":"element","tag":"em","props":{},"children":[{"type":"text","value":"number | string"}]}]},{"type":"element","tag":"td","props":{},"children":[{"type":"element","tag":"code","props":{"className":[]},"children":[{"type":"text","value":"56rpx"}]}]}]},{"type":"element","tag":"tr","props":{},"children":[{"type":"element","tag":"td","props":{},"children":[{"type":"text","value":"gutter"}]},{"type":"element","tag":"td","props":{},"children":[{"type":"text","value":"The spacing between grids, the default unit is "},{"type":"element","tag":"code","props":{"className":[]},"children":[{"type":"text","value":"px"}]}]},{"type":"element","tag":"td","props":{},"children":[{"type":"element","tag":"em","props":{},"children":[{"type":"text","value":"number | string"}]}]},{"type":"element","tag":"td","props":{},"children":[{"type":"element","tag":"code","props":{"className":[]},"children":[{"type":"text","value":"0"}]}]}]},{"type":"element","tag":"tr","props":{},"children":[{"type":"element","tag":"td","props":{},"children":[{"type":"text","value":"border"}]},{"type":"element","tag":"td","props":{},"children":[{"type":"text","value":"Whether to display the border"}]},{"type":"element","tag":"td","props":{},"children":[{"type":"element","tag":"em","props":{},"children":[{"type":"text","value":"boolean"}]}]},{"type":"element","tag":"td","props":{},"children":[{"type":"element","tag":"code","props":{"className":[]},"children":[{"type":"text","value":"true"}]}]}]},{"type":"element","tag":"tr","props":{},"children":[{"type":"element","tag":"td","props":{},"children":[{"type":"text","value":"center"}]},{"type":"element","tag":"td","props":{},"children":[{"type":"text","value":"Whether to center the grid content"}]},{"type":"element","tag":"td","props":{},"children":[{"type":"element","tag":"em","props":{},"children":[{"type":"text","value":"boolean"}]}]},{"type":"element","tag":"td","props":{},"children":[{"type":"element","tag":"code","props":{"className":[]},"children":[{"type":"text","value":"true"}]}]}]},{"type":"element","tag":"tr","props":{},"children":[{"type":"element","tag":"td","props":{},"children":[{"type":"text","value":"square"}]},{"type":"element","tag":"td","props":{},"children":[{"type":"text","value":"Whether to fix the grid to a square"}]},{"type":"element","tag":"td","props":{},"children":[{"type":"element","tag":"em","props":{},"children":[{"type":"text","value":"boolean"}]}]},{"type":"element","tag":"td","props":{},"children":[{"type":"element","tag":"code","props":{"className":[]},"children":[{"type":"text","value":"false"}]}]}]},{"type":"element","tag":"tr","props":{},"children":[{"type":"element","tag":"td","props":{},"children":[{"type":"text","value":"clickable"}]},{"type":"element","tag":"td","props":{},"children":[{"type":"text","value":"Whether to enable grid click feedback"}]},{"type":"element","tag":"td","props":{},"children":[{"type":"element","tag":"em","props":{},"children":[{"type":"text","value":"boolean"}]}]},{"type":"element","tag":"td","props":{},"children":[{"type":"element","tag":"code","props":{"className":[]},"children":[{"type":"text","value":"false"}]}]}]},{"type":"element","tag":"tr","props":{},"children":[{"type":"element","tag":"td","props":{},"children":[{"type":"text","value":"direction"}]},{"type":"element","tag":"td","props":{},"children":[{"type":"text","value":"The direction in which the grid content is arranged, the optional value is "},{"type":"element","tag":"code","props":{"className":[]},"children":[{"type":"text","value":"horizontal"}]}]},{"type":"element","tag":"td","props":{},"children":[{"type":"element","tag":"em","props":{},"children":[{"type":"text","value":"string"}]}]},{"type":"element","tag":"td","props":{},"children":[{"type":"element","tag":"code","props":{"className":[]},"children":[{"type":"text","value":"vertical"}]}]}]},{"type":"element","tag":"tr","props":{},"children":[{"type":"element","tag":"td","props":{},"children":[{"type":"text","value":"reverse"}]},{"type":"element","tag":"td","props":{},"children":[{"type":"text","value":"Whether to swap the positions of icons and text"}]},{"type":"element","tag":"td","props":{},"children":[{"type":"element","tag":"em","props":{},"children":[{"type":"text","value":"boolean"}]}]},{"type":"element","tag":"td","props":{},"children":[{"type":"element","tag":"code","props":{"className":[]},"children":[{"type":"text","value":"false"}]}]}]}]}]},{"type":"element","tag":"h3","props":{"id":"griditem-props"},"children":[{"type":"text","value":"GridItem Props"}]},{"type":"text","value":"\n\n\n\n\n\n\n\n\n\n\n\n\n\n\n\n\n\n\n\n\n\n\n\n\n\n\n\n\n\n\n\n\n\n\n\n\n\n\n\n\n\n\n\n\n\n\n\n\n\n\n\n\n\n"},{"type":"element","tag":"table","props":{},"children":[{"type":"element","tag":"thead","props":{},"children":[{"type":"element","tag":"tr","props":{},"children":[{"type":"element","tag":"th","props":{},"children":[{"type":"text","value":"Parameters"}]},{"type":"element","tag":"th","props":{},"children":[{"type":"text","value":"Description"}]},{"type":"element","tag":"th","props":{},"children":[{"type":"text","value":"Type"}]},{"type":"element","tag":"th","props":{},"children":[{"type":"text","value":"Default value"}]}]}]},{"type":"element","tag":"tbody","props":{},"children":[{"type":"element","tag":"tr","props":{},"children":[{"type":"element","tag":"td","props":{},"children":[{"type":"text","value":"text"}]},{"type":"element","tag":"td","props":{},"children":[{"type":"text","value":"text"}]},{"type":"element","tag":"td","props":{},"children":[{"type":"element","tag":"em","props":{},"children":[{"type":"text","value":"string"}]}]},{"type":"element","tag":"td","props":{},"children":[{"type":"text","value":"-"}]}]},{"type":"element","tag":"tr","props":{},"children":[{"type":"element","tag":"td","props":{},"children":[{"type":"text","value":"icon"}]},{"type":"element","tag":"td","props":{},"children":[{"type":"text","value":"Icon name or image link, equivalent to the "},{"type":"element","tag":"a","props":{"href":"/icon#props"},"children":[{"type":"text","value":"name attribute"}]},{"type":"text","value":" of the Icon component"}]},{"type":"element","tag":"td","props":{},"children":[{"type":"element","tag":"em","props":{},"children":[{"type":"text","value":"string"}]}]},{"type":"element","tag":"td","props":{},"children":[{"type":"text","value":"-"}]}]},{"type":"element","tag":"tr","props":{},"children":[{"type":"element","tag":"td","props":{},"children":[{"type":"text","value":"icon-prefix"}]},{"type":"element","tag":"td","props":{},"children":[{"type":"text","value":"Icon class name prefix, equivalent to the "},{"type":"element","tag":"a","props":{"href":"/icon#props"},"children":[{"type":"text","value":"class-prefix attribute"}]},{"type":"text","value":" of the Icon component"}]},{"type":"element","tag":"td","props":{},"children":[{"type":"element","tag":"em","props":{},"children":[{"type":"text","value":"string"}]}]},{"type":"element","tag":"td","props":{},"children":[{"type":"element","tag":"code","props":{"className":[]},"children":[{"type":"text","value":"z-icon"}]}]}]},{"type":"element","tag":"tr","props":{},"children":[{"type":"element","tag":"td","props":{},"children":[{"type":"text","value":"icon-color"}]},{"type":"element","tag":"td","props":{},"children":[{"type":"text","value":"Icon color, equivalent to the "},{"type":"element","tag":"a","props":{"href":"/icon#props"},"children":[{"type":"text","value":"color property"}]},{"type":"text","value":" of the Icon component"}]},{"type":"element","tag":"td","props":{},"children":[{"type":"element","tag":"em","props":{},"children":[{"type":"text","value":"string"}]}]},{"type":"element","tag":"td","props":{},"children":[{"type":"text","value":"-"}]}]},{"type":"element","tag":"tr","props":{},"children":[{"type":"element","tag":"td","props":{},"children":[{"type":"text","value":"dot"}]},{"type":"element","tag":"td","props":{},"children":[{"type":"text","value":"Whether to display the small red dot in the upper right corner of the icon"}]},{"type":"element","tag":"td","props":{},"children":[{"type":"element","tag":"em","props":{},"children":[{"type":"text","value":"boolean"}]}]},{"type":"element","tag":"td","props":{},"children":[{"type":"element","tag":"code","props":{"className":[]},"children":[{"type":"text","value":"false"}]}]}]},{"type":"element","tag":"tr","props":{},"children":[{"type":"element","tag":"td","props":{},"children":[{"type":"text","value":"badge"}]},{"type":"element","tag":"td","props":{},"children":[{"type":"text","value":"The content of the logo in the upper right corner of the icon"}]},{"type":"element","tag":"td","props":{},"children":[{"type":"element","tag":"em","props":{},"children":[{"type":"text","value":"number | string"}]}]},{"type":"element","tag":"td","props":{},"children":[{"type":"text","value":"-"}]}]},{"type":"element","tag":"tr","props":{},"children":[{"type":"element","tag":"td","props":{},"children":[{"type":"text","value":"badge-props"}]},{"type":"element","tag":"td","props":{},"children":[{"type":"text","value":"Customize the properties of the logo. The incoming object will be transparently passed to "},{"type":"element","tag":"a","props":{"href":"/badge#props"},"children":[{"type":"text","value":"Badge component props"}]}]},{"type":"element","tag":"td","props":{},"children":[{"type":"element","tag":"em","props":{},"children":[{"type":"text","value":"BadgeProps"}]}]},{"type":"element","tag":"td","props":{},"children":[{"type":"text","value":"-"}]}]}]}]},{"type":"element","tag":"h3","props":{"id":"griditem-events"},"children":[{"type":"text","value":"GridItem Events"}]},{"type":"text","value":"\n\n\n\n\n\n\n\n\n\n\n\n\n\n\n\n"},{"type":"element","tag":"table","props":{},"children":[{"type":"element","tag":"thead","props":{},"children":[{"type":"element","tag":"tr","props":{},"children":[{"type":"element","tag":"th","props":{},"children":[{"type":"text","value":"Event name"}]},{"type":"element","tag":"th","props":{},"children":[{"type":"text","value":"Description"}]},{"type":"element","tag":"th","props":{},"children":[{"type":"text","value":"Callback parameters"}]}]}]},{"type":"element","tag":"tbody","props":{},"children":[{"type":"element","tag":"tr","props":{},"children":[{"type":"element","tag":"td","props":{},"children":[{"type":"text","value":"click"}]},{"type":"element","tag":"td","props":{},"children":[{"type":"text","value":"Triggered when the grid is clicked"}]},{"type":"element","tag":"td","props":{},"children":[{"type":"element","tag":"em","props":{},"children":[{"type":"text","value":"event: MouseEvent"}]}]}]}]}]},{"type":"element","tag":"h3","props":{"id":"griditem-slots"},"children":[{"type":"text","value":"GridItem Slots"}]},{"type":"text","value":"\n\n\n\n\n\n\n\n\n\n\n\n\n\n\n\n\n\n\n\n\n\n"},{"type":"element","tag":"table","props":{},"children":[{"type":"element","tag":"thead","props":{},"children":[{"type":"element","tag":"tr","props":{},"children":[{"type":"element","tag":"th","props":{},"children":[{"type":"text","value":"Name"}]},{"type":"element","tag":"th","props":{},"children":[{"type":"text","value":"Description"}]}]}]},{"type":"element","tag":"tbody","props":{},"children":[{"type":"element","tag":"tr","props":{},"children":[{"type":"element","tag":"td","props":{},"children":[{"type":"text","value":"default"}]},{"type":"element","tag":"td","props":{},"children":[{"type":"text","value":"All contents of custom palace grid"}]}]},{"type":"element","tag":"tr","props":{},"children":[{"type":"element","tag":"td","props":{},"children":[{"type":"text","value":"icon"}]},{"type":"element","tag":"td","props":{},"children":[{"type":"text","value":"custom icon"}]}]},{"type":"element","tag":"tr","props":{},"children":[{"type":"element","tag":"td","props":{},"children":[{"type":"text","value":"text"}]},{"type":"element","tag":"td","props":{},"children":[{"type":"text","value":"Custom text"}]}]}]}]},{"type":"element","tag":"h2","props":{"id":"theme-customization"},"children":[{"type":"text","value":"Theme customization"}]},{"type":"element","tag":"h3","props":{"id":"style-variables"},"children":[{"type":"text","value":"Style variables"}]},{"type":"element","tag":"p","props":{},"children":[{"type":"text","value":"The component provides the following CSS variables, which can be used to customize styles. For usage, please refer to "},{"type":"element","tag":"a","props":{"href":"/config-provider"},"children":[{"type":"text","value":"ConfigProvider component"}]},{"type":"text","value":"."}]},{"type":"text","value":"\n\n\n\n\n\n\n\n\n\n\n\n\n\n\n\n\n\n\n\n\n\n\n\n\n\n\n\n\n\n\n\n\n\n\n\n\n\n\n\n\n"},{"type":"element","tag":"table","props":{},"children":[{"type":"element","tag":"thead","props":{},"children":[{"type":"element","tag":"tr","props":{},"children":[{"type":"element","tag":"th","props":{},"children":[{"type":"text","value":"Name"}]},{"type":"element","tag":"th","props":{},"children":[{"type":"text","value":"Default"}]},{"type":"element","tag":"th","props":{},"children":[{"type":"text","value":"Description"}]}]}]},{"type":"element","tag":"tbody","props":{},"children":[{"type":"element","tag":"tr","props":{},"children":[{"type":"element","tag":"td","props":{},"children":[{"type":"text","value":"--z-grid-item-content-padding"}]},{"type":"element","tag":"td","props":{},"children":[{"type":"element","tag":"em","props":{},"children":[{"type":"text","value":"var(--z-padding-md) var(--z-padding-xs)"}]}]},{"type":"element","tag":"td","props":{},"children":[{"type":"text","value":"-"}]}]},{"type":"element","tag":"tr","props":{},"children":[{"type":"element","tag":"td","props":{},"children":[{"type":"text","value":"--z-grid-item-content-background"}]},{"type":"element","tag":"td","props":{},"children":[{"type":"element","tag":"em","props":{},"children":[{"type":"text","value":"var(--z-background-2)"}]}]},{"type":"element","tag":"td","props":{},"children":[{"type":"text","value":"-"}]}]},{"type":"element","tag":"tr","props":{},"children":[{"type":"element","tag":"td","props":{},"children":[{"type":"text","value":"--z-grid-item-content-active-color"}]},{"type":"element","tag":"td","props":{},"children":[{"type":"element","tag":"em","props":{},"children":[{"type":"text","value":"var(--z-active-color)"}]}]},{"type":"element","tag":"td","props":{},"children":[{"type":"text","value":"-"}]}]},{"type":"element","tag":"tr","props":{},"children":[{"type":"element","tag":"td","props":{},"children":[{"type":"text","value":"--z-grid-item-icon-size"}]},{"type":"element","tag":"td","props":{},"children":[{"type":"element","tag":"em","props":{},"children":[{"type":"text","value":"56rpx"}]}]},{"type":"element","tag":"td","props":{},"children":[{"type":"text","value":"-"}]}]},{"type":"element","tag":"tr","props":{},"children":[{"type":"element","tag":"td","props":{},"children":[{"type":"text","value":"--z-grid-item-text-color"}]},{"type":"element","tag":"td","props":{},"children":[{"type":"element","tag":"em","props":{},"children":[{"type":"text","value":"var(--z-text-color)"}]}]},{"type":"element","tag":"td","props":{},"children":[{"type":"text","value":"-"}]}]},{"type":"element","tag":"tr","props":{},"children":[{"type":"element","tag":"td","props":{},"children":[{"type":"text","value":"--z-grid-item-text-font-size"}]},{"type":"element","tag":"td","props":{},"children":[{"type":"element","tag":"em","props":{},"children":[{"type":"text","value":"var(--z-font-size-sm)"}]}]},{"type":"element","tag":"td","props":{},"children":[{"type":"text","value":"-"}]}]}]}]},{"type":"element","tag":"style","props":{},"children":[{"type":"text","value":"html .default .shiki span {color: var(--shiki-default);background: var(--shiki-default-bg);font-style: var(--shiki-default-font-style);font-weight: var(--shiki-default-font-weight);text-decoration: var(--shiki-default-text-decoration);}html .shiki span {color: var(--shiki-default);background: var(--shiki-default-bg);font-style: var(--shiki-default-font-style);font-weight: var(--shiki-default-font-weight);text-decoration: var(--shiki-default-text-decoration);}html .dark .shiki span {color: var(--shiki-dark);background: var(--shiki-dark-bg);font-style: var(--shiki-dark-font-style);font-weight: var(--shiki-dark-font-weight);text-decoration: var(--shiki-dark-text-decoration);}html.dark .shiki span {color: var(--shiki-dark);background: var(--shiki-dark-bg);font-style: var(--shiki-dark-font-style);font-weight: var(--shiki-dark-font-weight);text-decoration: var(--shiki-dark-text-decoration);}"}]}],"toc":{"title":"","searchDepth":2,"depth":2,"links":[{"id":"introduce","depth":3,"text":"introduce"},{"id":"code-demo","depth":2,"text":"Code Demo","children":[{"id":"basic-usage","depth":3,"text":"Basic usage"},{"id":"customize-the-number-of-columns","depth":3,"text":"Customize the number of columns"},{"id":"custom-content","depth":3,"text":"Custom content"},{"id":"square-grid","depth":3,"text":"Square grid"},{"id":"grid-spacing","depth":3,"text":"Grid spacing"},{"id":"contents-arranged-horizontally","depth":3,"text":"Contents arranged horizontally"},{"id":"logo-tips","depth":3,"text":"Logo Tips"}]},{"id":"api","depth":2,"text":"API","children":[{"id":"grid-props","depth":3,"text":"Grid Props"},{"id":"griditem-props","depth":3,"text":"GridItem Props"},{"id":"griditem-events","depth":3,"text":"GridItem Events"},{"id":"griditem-slots","depth":3,"text":"GridItem Slots"}]},{"id":"theme-customization","depth":2,"text":"Theme customization","children":[{"id":"style-variables","depth":3,"text":"Style variables"}]}]}},"_type":"markdown","_id":"content:en:grid.md","_source":"content","_file":"en/grid.md","_extension":"md"}